LICENSE
MANIFEST.in
README.md
requirements.txt
setup.py
booru/__init__.py
booru.egg-info/PKG-INFO
booru.egg-info/SOURCES.txt
booru.egg-info/dependency_links.txt
booru.egg-info/requires.txt
booru.egg-info/top_level.txt
booru/client/__init__.py
booru/client/atfbooru.py
booru/client/behoimi.py
booru/client/danbooru.py
booru/client/derpibooru.py
booru/client/e621.py
booru/client/e926.py
booru/client/furbooru.py
booru/client/gelbooru.py
booru/client/hypnohub.py
booru/client/konachan.py
booru/client/konachan_net.py
booru/client/lolibooru.py
booru/client/paheal.py
booru/client/realbooru.py
booru/client/rule34.py
booru/client/safebooru.py
booru/client/tbib.py
booru/client/xbooru.py
booru/client/yandere.py
booru/utils/__init__.py
booru/utils/constant.py
booru/utils/fetch.py