Metadata-Version: 2.4
Name: booru
Version: 1.2.1
Summary: Python bindings for Booru imageboards
Home-page: https://github.com/sinkaroid/booru
Author: sinkaroid
Author-email: anakmancasan@gmail.com
License: MIT
Project-URL: CI, https://github.com/sinkaroid/booru/actions
Project-URL: Funding, https://github.com/sponsors/sinkaroid
Project-URL: Issue tracker, https://github.com/sinkaroid/booru/issues/new/choose
Project-URL: Documentation, https://sinkaroid.github.io/booru
Project-URL: Discord, https://discord.gg/8wj4vM5hHM
Keywords: booru,gelbooru,rule34,safebooru,xbooru,tbib,realbooru,hypnohub,danbooru,atfbooru,yandere,konachan,konachan.net,lolibooru,e621,e926,derpibooru,furbooru,behoimi,paheal
Classifier: Framework :: AsyncIO
Classifier: Development Status :: 3 - Alpha
Classifier: Intended Audience :: Developers
Classifier: License :: OSI Approved :: MIT License
Classifier: Natural Language :: English
Classifier: Operating System :: OS Independent
Classifier: Programming Language :: Python :: 3.7
Classifier: Programming Language :: Python :: 3.8
Classifier: Programming Language :: Python :: 3.9
Classifier: Programming Language :: Python :: 3.10
Classifier: Topic :: Artistic Software
Classifier: Topic :: Games/Entertainment
Classifier: Topic :: Internet :: WWW/HTTP
Classifier: Topic :: Software Development :: Libraries
Classifier: Topic :: Software Development :: Build Tools
License-File: LICENSE
Requires-Dist: aiohttp>=3.12.13
Requires-Dist: beautifulsoup4>=4.13.4
Requires-Dist: xmltodict>=0.14.2
Dynamic: author
Dynamic: author-email
Dynamic: classifier
Dynamic: description
Dynamic: description-content-type
Dynamic: home-page
Dynamic: keywords
Dynamic: license
Dynamic: license-file
Dynamic: project-url
Dynamic: requires-dist
Dynamic: summary
